fsmdot/__init__.py
fsmdot/dfa.py
fsmdot/error.py
fsmdot/fsm.py
fsmdot/nfa.py
fsmdot-0.0.1.dist-info/LICENSE
fsmdot-0.0.1.dist-info/METADATA
fsmdot-0.0.1.dist-info/WHEEL
fsmdot-0.0.1.dist-info/top_level.txt
fsmdot-0.0.1.dist-info/zip-safe
fsmdot-0.0.1.dist-info/RECORD
