Metadata-Version: 2.1
Name: fsmdot
Version: 0.0.1
Summary: 
Home-page: https://github.com/Quentin18/fsmdot
Author: Quentin Deschamps
Author-email: quentindeschamps18@gmail.com
License: MIT
Project-URL: Travis, https://travis-ci.org/github/Quentin18/fsmdot/
Project-URL: Source Code, https://github.com/Quentin18/fsmdot/
Keywords: fsm automata dfa nfa
Platform: any
Classifier: License :: OSI Approved :: MIT License
Classifier: Natural Language :: English
Classifier: Operating System :: OS Independent
Classifier: Programming Language :: Python :: 3
Classifier: Programming Language :: Python :: 3.6
Classifier: Programming Language :: Python :: 3.7
Classifier: Programming Language :: Python :: 3.8
Classifier: Topic :: Education
Classifier: Topic :: Scientific/Engineering
Requires-Python: >=3.6
Requires-Dist: pygraphviz
Requires-Dist: tabulate
